lazylee_mcp_test/server.py
lazylee_mcp_test-0.8.0.dist-info/licenses/LICENSE
lazylee_mcp_test-0.8.0.dist-info/METADATA
lazylee_mcp_test-0.8.0.dist-info/WHEEL
lazylee_mcp_test-0.8.0.dist-info/entry_points.txt
lazylee_mcp_test-0.8.0.dist-info/top_level.txt
lazylee_mcp_test-0.8.0.dist-info/RECORD
