Metadata-Version: 2.4
Name: lazylee-mcp-test
Version: 0.8.0
Summary: Add your description here
Requires-Python: >=3.12
License-File: LICENSE
Requires-Dist: httpx>=0.28.1
Requires-Dist: mcp[cli]>=1.7.1
Requires-Dist: mcp>=1.0.0
Dynamic: license-file
